{"id":"UPQ-01-02-242","source":{"id":"UPMP-01-0037","english":"U Har Shein Bwe","myanmar":"ဦးဟာရှိန်းဘွေ"},"house":"First Amyotha Hluttaw","session":"Second Regular Session","date":"18-Oct-11","description":{"english":"Access to drinking in Mindat","myanmar":"မင်းတပ်မြို့တွင် သောက်သုံးရေဖူလုံစွာရရှိနိုင်ရန် သက်ဆိုင်ရာဝန်ကြီးဌာနမှ ကူညီပံ့ပိုးပေးရန် အစီစဉ် ရှိ/မရှိ နှင့် စပ်လျဉ်းသည့် မေးခွန်း"},"issue":"Development","respondent":{"name":"Lt-Gen Thein Htay","position":"Border Affairs Minister"},"purpose":"Representation"}