{"id":"UPQ-01-02-265","source":{"id":"UPMP-01-0174","english":"Dr. Khin Shwe","myanmar":"ဒေါက်တာခင်ရွှေ"},"house":"First Amyotha Hluttaw","session":"Second Regular Session","date":"24-Oct-11","description":{"english":"Repairing tributories in Twantay to prevent flood","myanmar":"တွံတေးမြို့နယ်၊ ခတ္တိယရေကျော်ချောင်းဟောင်း ၅ မိုင်နှင့် ရေတွင်းကုန်း တမာတကော ရေသွင်း ရေနုတ်မြောင်း ၆ မိုင်အား ရေကြီးမှုမှ ကာကွယ်ရန်အတွက် ပြန်လည်ပြုပြင်ပေးရန် အစီအစဉ် ရှိ/မရှိ နှင့် စပ်လျဉ်းသည့် မေးခွန်း"},"issue":"Infrasturctural Development","respondent":{"name":"U Min Zaw","position":"Deputy Agriculture and Irrigation Minister"},"purpose":"Representation"}