{"id":"UPQ-01-02-083","source":{"id":"UPMP-01-0114","english":"U Nyo Tun","myanmar":"ဦးညိုထွန်း"},"house":"First Amyotha Hluttaw","session":"Second Regular Session","date":"9-Sep-11","description":{"english":"Hydropower project near Koekanttan village in An","myanmar":"ရခိုင်ပြည်နယ် အမ်းမြို့အထက်ပိုင်း ကိုးကန့်တန်းရွာအနီး တည်ဆောက်လျက်ရှိသော ရေအားလျှပ်စစ်ဓါတ်အားစီမံကိန်း ပြီးစီးမှုအခြေအနေနှင့် အမ်းမြို့ပေါ်ရှိရပ်ကွက်များတွင် လျှပ်စစ်မီးလင်းချိန်တိုးပေးနိုင်ရန် အစီအစဉ် ရှိ/မရှိ နှင့် စပ်လျဉ်းသည့် မေးခွန်း"},"issue":"Infrasturctural Development","respondent":{"name":"U Zaw Min","position":"Electric Power Minister"}}