{"id":"UPQ-01-02-033","source":{"id":"UPMP-01-0127","english":"U Aung Chit Lwin","myanmar":"ဦးအောင်ချစ်လွင်"},"house":"First Amyotha Hluttaw","session":"Second Regular Session","date":"31-Aug-11","description":{"english":"Appointment of doctors to Hkamti hospital","myanmar":"ခန္တီးခရိုင်၊ ခုတင်(၁၀၀)ဆံ့ ပြည်သူ့ဆေးရုံကြီးတွင် လိုအပ်နေသည့် အထူးကုဆရာဝန်များ၊ လက်ထောက်ဆရာဝန်များ၊ ဆရာမများနှင့် ဝန်ထမ်းအင်အား တိုးချဲ့ခန့်ထားပေးရန် အစီအစဉ် ရှိ/မရှိ နှင့် စပ်လျဉ်းသည့်မေးခွန်း"},"issue":"Health","respondent":{"name":"Dr. Pe Thet Khin","position":"Health Minister"},"purpose":"Representation"}