{"id":"LWMP-01-0005","name":{"english":"U Ko Gyi","myanmar":"ဦးကိုကြီး"},"questions":[{"id":"LWQ-01-02-301","house":"First Pyithu Hluttaw","session":"Second Regular Session","date":"24-Oct-11","description":{"english":"Importing animal feeds and cooking palm oil","myanmar":""},"issue":"Breeding","respondent":{"name":"Dr. Pwint Hsan","position":"Deputy Commerce Minister"}},{"id":"LWQ-01-03-072","house":"First Pyithu Hluttaw","session":"Third Regular Session","date":"29-Feb-12","description":{"english":"Demarcation of ward's municipal areas","myanmar":""},"issue":"Administration","respondent":{"name":"Lt-Gen Ko Ko","position":"Home Minister"}},{"id":"LWQ-01-04-115","house":"First Pyithu Hluttaw","session":"Fourth Regular Session","date":"15-Aug-12","description":{"english":"Loans to farmers","myanmar":""},"issue":"Agriculture","respondent":{"name":"U Khin Zaw","position":"Deputy Agriculture and Irrigation Minister"}},{"id":"LWQ-01-04-117","house":"First Pyithu Hluttaw","session":"Fourth Regular Session","date":"16-Aug-12","description":{"english":"Export of cooking oil","myanmar":""},"issue":"Business","respondent":{"name":"Dr Pwint Hsan","position":"Deputy Commerce Minister"}},{"id":"LWQ-01-04-127","house":"First Pyithu Hluttaw","session":"Fourth Regular Session","date":"22-Aug-12","description":{"english":"Anti-illegal immigration measures","myanmar":""},"issue":"Administration","respondent":{"name":"U Kyaw Kyaw Win","position":"Deputy Immigration and Population Minister"}},{"id":"LWQ-01-04-156","house":"First Pyithu Hluttaw","session":"Fourth Regular Session","date":"3-Sep-12","description":{"english":"Road accident prevention","myanmar":""},"issue":"Administration","respondent":{"name":"Police Maj-Gen Kyaw Kyaw Tun","position":"Deputy Home Minister"}},{"id":"LWQ-01-07-014","house":"First Pyithu Hluttaw","session":"Seventh Regular Session","date":"26-Jun-13","description":{"english":"Sideeffect of Cloud point 8 oil","myanmar":""},"issue":"Health","respondent":{"name":"Dr. Win Myint","position":"Deputy Health Minister"}},{"id":"LWQ-01-07-064","house":"First Pyithu Hluttaw","session":"Seventh Regular Session","date":"4-Jul-13","description":{"english":"Supplying Antidote","myanmar":""},"issue":"Health","respondent":{"name":"U Thein Aung","position":"Deputy Industry Minister"}},{"id":"LWQ-01-07-225","house":"First Pyithu Hluttaw","session":"Seventh Regular Session","date":"23-Aug-13","description":{"english":"Accessibility of strains for farmers","myanmar":""},"issue":"Agriculture","respondent":{"name":"U Ohn Than","position":"Deputy Agriculture and Irrigation Minister"}},{"id":"LWQ-01-07-238","house":"First Pyithu Hluttaw","session":"Seventh Regular Session","date":"28-Aug-13","description":{"english":"Allowing qualified military personnel to attend post-graduate courses","myanmar":""},"issue":"Education","respondent":{"name":"Maj-Gen Kyaw Nyunt","position":"Deputy Defence Minister"}},{"id":"LWQ-01-08-037","house":"First Pyithu Hluttaw","session":"Eight Regular Session","date":"8-Oct-13","description":{"english":"Weight and quality control of oil","myanmar":""},"issue":"Health","respondent":{"name":"Dr Pwint San","position":"Deputy Commerce Minister"}},{"id":"LWQ-01-08-064","house":"First Pyithu Hluttaw","session":"Eight Regular Session","date":"14-Oct-13","description":{"english":"Developing Small Bussiness","myanmar":""},"issue":"Business","respondent":{"name":"U Myo Aung","position":"Deputy Industry Minister"}},{"id":"LWQ-01-08-141","house":"First Pyithu Hluttaw","session":"Eight Regular Session","date":"14-Nov-13","description":{"english":"Quality of import framented soya bean from China include Melimine","myanmar":""},"issue":"Health","respondent":{"name":"Dr Than Aung","position":"Deputy Health Minister"}},{"id":"LWQ-01-09-115","house":"First Pyithu Hluttaw","session":"Ninth Regular Session","date":"24-Feb-14","description":{"english":"Giving small and micro loan for the small and micro industry in Mandalay","myanmar":""},"issue":"Business","respondent":{"name":"U Myo Aung","position":"Deputy Industery Minister"}},{"id":"LWQ-01-09-170","house":"First Pyithu Hluttaw","session":"Ninth Regular Session","date":"18-Mar-14","description":{"english":"Information about the oil importing and crops exporting's icome,","myanmar":""},"issue":"Business","respondent":{"name":"Dr Pwint San","position":"Deputy Commerce Minister"}},{"id":"LWQ-01-10-071","house":"First Pyithu Hluttaw","session":"Tenth Regular Session","date":"16-Jun-14","description":{"english":"Plan of losening the loss of growing peanut in sand land and island","myanmar":""},"issue":"Agriculture","respondent":{"name":"U Oh Than","position":"Deputy Agriculture and irragation Minister"}},{"id":"LWQ-01-10-093","house":"First Pyithu Hluttaw","session":"Tenth Regular Session","date":"18-Jun-14","description":{"english":"Supporting Mingalardone National Refitting Hospital","myanmar":""},"issue":"Health","respondent":{"name":"Dr Than Aung","position":"Deputy Health Minister"}},{"id":"LWQ-01-10-101","house":"First Pyithu Hluttaw","session":"Tenth Regular Session","date":"20-Jun-14","description":{"english":"Plan for solving the difficulties of the farmers because of higher price of the cows","myanmar":""},"issue":"Agriculture","respondent":{"name":"U Ohn Than","position":"Deputy Agriculture and Irragation Mininster"}},{"id":"LWQ-01-11-130","house":"First Pyithu Hluttaw","session":"Eleventh Regular Session","date":"20-Oct-14","description":{"english":"Chang the Policy of Import n Export for oil palm","myanmar":""},"issue":"Business","respondent":{"name":"Dr. Pwint Hsan","position":"Deputy Commerce Minister"}},{"id":"CBQ-01-01-009","house":"First Pyithu Hluttaw","session":"First Regular Session","date":"25-Mar-11","description":{"english":"Drafting anti-trust law","myanmar":""},"issue":"Business","respondent":{"name":"U Tin Naing Thein","position":"Commerce Minister"}}]}