{"id":"UPMP-01-0070","name":{"english":"U Sein Myint","myanmar":"ဦးစိန်မြင့်"},"motions":[{"id":"UP-01-05-010","submitted_date":"6-Nov-12","house":"First Amyotha Hluttaw","session":"Fifth Regular Session","description":{"english":"Preparations for household registration of ethnic nationalities","myanmar":"နိုင်ငံတော်အနေဖြင့် နိုင်ငံသားများ၏ မှတ်ပုံတင်နှင့် အိမ်ထောင်စုစာရင်းများ ပြုလုပ်ရာတွင် တိုင်းရင်းသားမျိုးနွယ်စု များ၏ လူဦးရေစာရင်း တိကျမှန်ကန်ရေးနှင့် တိုင်းရင်းသားမျိုးနွယ်စုများ၏ အမည်နာမ ရေးသားဖြည့်စွက်ရာတွင် မှားယွင်းမှုမရှိစေရေးအတွက် ဒေသခံတိုင်းရင်းသားများ ပါဝင်သော အဖွဲ့ဖြင့် ပူးပေါင်းလျက် လိုအပ်သော ကြိုတင်ပြင်ဆင် ဖွဲ့စည်းမှုများ ဆောင်ရွက်ပေးရန် ပြည်ထောင်စုအစိုးရအား တိုက်တွန်းကြောင်း အဆို"},"issue":"Social Welfare","purpose":"Scrutiny","status":"Approved","response_date":"15-Nov-12","respondent":{"name":"U Win Myint","position":"Deputy Immigration and Population Minister"}},{"id":"UP-01-06-002","submitted_date":"9-Jan-13","house":"First Amyotha Hluttaw","session":"Sixth Regular Session","description":{"english":"Teaching the democracy pratice at primay school","myanmar":"လူငယ်ဗဟိုပြု အခြေခံပညာ အထက်တန်းကျောင်းများတွင် ဒီမိုကရေစီကျင့်စဉ်များ လေ့ကျင့်ပျိုးထောင်ပေးရန် ပြည်ထောင်စု အစိုးရအား တိုက်တွန်းကြောင်းအဆို"},"issue":"Education","purpose":"Scrutiny","status":"Approved","response_date":"4-Feb-13","respondent":{"name":"U Aye Q","position":"Deputy Education Minister"}},{"id":"UP-01-06-008","submitted_date":"22-Jan-13","house":"First Amyotha Hluttaw","session":"Sixth Regular Session","description":{"english":"Improvement of the monastic education system","myanmar":"ရှေးခေတ်မြန်မာ့ ယဉ်ကျေးမှုကို အခြေခံသည့် ကျေးလက်ဗဟိုပြု ရွာဦးဘုန်းတော်ကြီးကျောင်း ပညာရေးစနစ် အဆင့်မြှင့်တင်ပေးရန် ပြည်ထောင်စုအစိုးရအား တိုက်တွန်းကြောင်းအဆို"},"issue":"Education","purpose":"Scrutiny","status":"Recorded","respondent":{}},{"id":"UP-01-06-012","submitted_date":"1-Feb-13","house":"First Amyotha Hluttaw","session":"Sixth Regular Session","description":{"english":"Opening The Center of Village Youth at border","myanmar":"နယ်စပ်နှင့် တောင်တန်း ဒေသများတွင်အနာဂတ်ဖွံ့ဖြိုးရေးအတွက် ကျေးလက်ဗဟိုပြုလူငယ် ပျိုးခင်းသင်တန်းကျောင်း စတင်လှစ်ပေးရန် ပြည်ထောင်စုအစိုးရအား တိုက်တွန်းကြောင်းအဆို "},"issue":"Education","purpose":"Scrutiny","status":"Approved","response_date":"22-Feb-13","respondent":{"name":"Dr Maung Maung Htay","position":"Religious Minister"}}]}