{"id":"UP-01-07-010","source":{"id":"UPMP-01-0173","english":"Dr. Myint Kyi","myanmar":"ဒေါက်တာမြင့််ကြည်"},"submitted_date":"4-Jul-13","house":"First Amyotha Hluttaw","session":"Seventh Regular Session","description":{"english":"To Carry out River water Treatment","myanmar":"မြစ်-ချောင်း-ရေလှောင်တမံများမှ ရေကိုသန့်ရှင်းအောင် ဆောင်ရွက်ပေးရန် (River Water Treatment) ပြည်ထောင်စုအစိုးရအား တိုက်တွန်းကြောင်း အဆို"},"issue":"Environment","purpose":"Scrutiny","status":"Approved","response_date":"","respondent":{"name":"U Win Htun","position":"Enviromental Conservation and Forestry Minister"}}