{"id":"UP-01-02-021","source":{"id":"UPMP-01-0015","english":"U Myint Tun","myanmar":"ဦးမြင့်ထွန်း"},"submitted_date":"1-Sep-11","house":"First Amyotha Hluttaw","session":"Second Regular Session","description":{"english":"Making Vrigin Land into Agricultural Land","myanmar":"မြေလွတ်မြေရိုင်းများကို လယ်ယာမြေအဖြစ် တိုးချဲ့ဖော်ထုတ်ပေးရန် ပြည်ထောင်စုအစိုးရအား တိုက်တွန်းကြောင်း အဆို"},"issue":"Agriculture","purpose":"Scrutiny","status":"Withdrawn","response_date":"2-Sep-11","respondent":{"name":"U Myint Hlaing","position":"Agriculture and Irrigation Minister"}}