{"id":"UPMP-01-0103","name":{"english":"U Zaw Naing Oo","myanmar":"ဦးဇော်နိုင်ဦး"},"motions":[{"id":"UP-01-03-006","submitted_date":"30-Jan-12","house":"First Amyotha Hluttaw","session":"Third Regular Session","description":{"english":"Helping ethnic people who live in the villages with no peace","myanmar":"နိုင်ငံအတွင်းရှိ မြို့ပြများနှင့်နီးပြီး ငြိမ်းချမ်းမှုမရှိသော ဒေသများနှင့်ဆက်စပ်လျက်ရှိသော ကျေးရွာများတွင် နေထိုင်ကြသည့် တိုင်းရင်းသား ပြည်သူများ၏လိုအပ်ချက်နှင့် တွေ့ကြုံခံစားနေရသော အခက်အခဲများအား စစ်ကြောင်းကြီးများနှင့်သွားရောက်၍ တတ်နိုင်သမျှကူညီ ဆောင်ရွက်ပေးပါရန် ပြည်ထောင်စု အစိုးရအား တိုက်တွန်းကြောင်းအဆို "},"issue":"Social Welfare","purpose":"Scrutiny","status":"Approved","response_date":"17-Feb-12","respondent":{"name":"Lt. Gen Ko Ko","position":"Home Minister"}}]}